_titanlib.cpython-38-x86_64-linux-gnu.so
titanlib.py
titanlib-0.3.3.dist-info/WHEEL
titanlib-0.3.3.dist-info/METADATA
titanlib-0.3.3.dist-info/top_level.txt
titanlib-0.3.3.dist-info/RECORD
titanlib.libs/libgslcblas-15b2d0fe.so.0.0.0
titanlib.libs/libgomp-3300acd3.so.1.0.0
titanlib.libs/libgsl-b885fd68.so.0.14.0
