Metadata-Version: 2.1
Name: titanlib
Version: 0.3.3
Summary: A quality control toolbox
Home-page: https://github.com/metno/titanlib
Author: Thomas Nipen
Author-email: thomasn@met.no
License: LGPL-3
Keywords: meteorology quality control observation weather
Classifier: Development Status :: 4 - Beta
Classifier: Intended Audience :: Science/Research
Classifier: Topic :: Scientific/Engineering :: Atmospheric Science
Classifier: Topic :: Scientific/Engineering :: Information Analysis
Classifier: License :: OSI Approved :: GNU Lesser General Public License v3 (LGPLv3)
Classifier: Programming Language :: Python :: 2
Classifier: Programming Language :: Python :: 2.6
Classifier: Programming Language :: Python :: 2.7
Classifier: Programming Language :: Python :: 3.6
Classifier: Programming Language :: Python :: 3.7
Requires-Dist: numpy (>=1.16)
